sofastats_examples/__init__.py
sofastats_examples/files/books.csv
sofastats_examples/files/education.csv
sofastats_examples/files/people.csv
sofastats_examples/files/properties.csv
sofastats_examples/files/sofastats_demo.db
sofastats_examples/files/sort_orders.yaml
sofastats_examples/files/sports.csv
sofastats_examples/output/default_location_for_demo_output
sofastats_examples/py.typed
sofastats_examples/scripts/__init__.py
sofastats_examples/scripts/conf.py
sofastats_examples/scripts/demo_charts.py
sofastats_examples/scripts/demo_combined.py
sofastats_examples/scripts/demo_custom_styles.py
sofastats_examples/scripts/demo_stats.py
sofastats_examples/scripts/demo_tables.py
sofastats_examples-0.1.0.dist-info/WHEEL
sofastats_examples-0.1.0.dist-info/METADATA
sofastats_examples-0.1.0.dist-info/RECORD
