Metadata-Version: 2.3
Name: sofastats-examples
Version: 0.1.0
Summary: Working example scripts demonstrating sofastats_lib
Author: Grant Paton-Simpson
Author-email: Grant Paton-Simpson <grant@p-s.co.nz>
Requires-Dist: sofastats-lib
Requires-Python: >=3.12
